.DS_Store
tdprepview/__init__.py
tdprepview/autoprep/__init__.py
tdprepview/autoprep/_builder.py
tdprepview/autoprep/_checker.py
tdprepview/pipeline/_DAG.py
tdprepview/pipeline/__init__.py
tdprepview/pipeline/_pipeline.py
tdprepview/pipeline/_plotter.py
tdprepview/pipeline/_serializer.py
tdprepview/pipeline/_utils.py
tdprepview/preprocessing/_TODO.py
tdprepview/preprocessing/__init__.py
tdprepview/preprocessing/_dimensionality_reduction.py
tdprepview/preprocessing/_discretize.py
tdprepview/preprocessing/_encoding.py
tdprepview/preprocessing/_features.py
tdprepview/preprocessing/_hashing.py
tdprepview/preprocessing/_impute.py
tdprepview/preprocessing/_miscellaneous.py
tdprepview/preprocessing/_preprocessing.py
tdprepview/preprocessing/_transform.py
tdprepview/preprocessing/_utils.py
tdprepview/sql/__init__.py
tdprepview/sql/generator/__init__.py
tdprepview/sql/generator/_utils.py
tdprepview/sql/generator/multicol.py
tdprepview/sql/generator/singlecol.py
tdprepview/sql/templates/from.sql
tdprepview/sql/templates/replaceview.sql
tdprepview/sql/templates/withas.sql
tdprepview/statistics/__init__.py
tdprepview/statistics/collector.py
tdprepview/statistics/collector_sklearn.py
tdprepview/statistics/collector_vantage.py
tdprepview/tests/__init__.py
tdprepview-1.5.0.dist-info/AUTHORS.md
tdprepview-1.5.0.dist-info/LICENSE
tdprepview-1.5.0.dist-info/METADATA
tdprepview-1.5.0.dist-info/WHEEL
tdprepview-1.5.0.dist-info/top_level.txt
tdprepview-1.5.0.dist-info/RECORD
