Metadata-Version: 2.1
Name: tdprepview
Version: 1.5.0
Summary: Python Package that creates Data Preparation Pipeline in Teradata-SQL in Views
Author: Martin Hillebrand
Author-email: martin.hillebrand@teradata.com
Keywords: tdprepview,teradata,database,preprocessing,data engineering,data science
Classifier: Development Status :: 4 - Beta
Classifier: Intended Audience :: Developers
Classifier: License :: OSI Approved :: GNU General Public License v3 (GPLv3)
Classifier: Natural Language :: English
Classifier: Programming Language :: Python :: 3
Classifier: Programming Language :: Python :: 3.8
Classifier: Programming Language :: Python :: 3.9
Classifier: Programming Language :: Python :: 3.10
Classifier: Programming Language :: Python :: 3.11
Classifier: Topic :: Database
Requires-Python: >=3.8
License-File: LICENSE
License-File: AUTHORS.md
Requires-Dist: teradataml >=17.10.00.02
Requires-Dist: pandas
Requires-Dist: numpy
Requires-Dist: scikit-learn >=1.3.0
Provides-Extra: plot
Requires-Dist: plotly >=5.0 ; extra == 'plot'
Requires-Dist: seaborn >=0.11 ; extra == 'plot'
